{
  "type": "FeatureCollection",
  "hc-transform": {
    "default": {
      "crs": "+proj=longlat +ellps=WGS84 +units=m +no_defs"
    }
  },
  "features": [
    {
      "type": "Feature",
      "properties": {
        "osm-relation-id": 7138166,
        "name": "Phường Linh Chiểu",
        "hc-key": "phuong-linh-chieu",
        "district": "Quận Thủ Đức"
      },
      "geometry": {
        "type": "MultiPolygon",
        "coordinates": [
          [
            [
              [
                106.7549661,
                10.8511412
              ],
              [
                106.7550249,
                10.8511683
              ],
              [
                106.7552286,
                10.8511904
              ],
              [
                106.7557114,
                10.8511483
              ],
              [
                106.756039,
                10.8511418
              ],
              [
                106.7570903,
                10.851263
              ],
              [
                106.7576245,
                10.8511322
              ],
              [
                106.7581071,
                10.8509583
              ],
              [
                106.7586347,
                10.8506443
              ],
              [
                106.7619488,
                10.8504679
              ],
              [
                106.7627923,
                10.8508571
              ],
              [
                106.7669872,
                10.8504858
              ],
              [
                106.7673155,
                10.8503326
              ],
              [
                106.7677515,
                10.849871
              ],
              [
                106.7682294,
                10.8497623
              ],
              [
                106.7720997,
                10.8496714
              ],
              [
                106.7722379,
                10.8496468
              ],
              [
                106.7733003,
                10.8496112
              ],
              [
                106.7737406,
                10.8501289
              ],
              [
                106.7743743,
                10.8515041
              ],
              [
                106.7743529,
                10.8518268
              ],
              [
                106.7741873,
                10.8521782
              ],
              [
                106.7730805,
                10.8539722
              ],
              [
                106.7729713,
                10.8544642
              ],
              [
                106.7719011,
                10.8540432
              ],
              [
                106.7716954,
                10.8539846
              ],
              [
                106.7715016,
                10.8539939
              ],
              [
                106.7699543,
                10.8541518
              ],
              [
                106.7694616,
                10.8542373
              ],
              [
                106.7687296,
                10.8544593
              ],
              [
                106.7677033,
                10.8550745
              ],
              [
                106.7668871,
                10.8555832
              ],
              [
                106.766545,
                10.8558782
              ],
              [
                106.7663428,
                10.8562132
              ],
              [
                106.7661379,
                10.8564661
              ],
              [
                106.7648889,
                10.8567785
              ],
              [
                106.764378,
                10.8569274
              ],
              [
                106.7641078,
                10.8570927
              ],
              [
                106.7638569,
                10.8573328
              ],
              [
                106.763587,
                10.8576537
              ],
              [
                106.7628601,
                10.8586629
              ],
              [
                106.7621925,
                10.8594226
              ],
              [
                106.7615379,
                10.8605013
              ],
              [
                106.7613175,
                10.860683
              ],
              [
                106.7609034,
                10.8608993
              ],
              [
                106.7607948,
                10.8606442
              ],
              [
                106.7604046,
                10.8601149
              ],
              [
                106.7598558,
                10.8596518
              ],
              [
                106.7595062,
                10.8593124
              ],
              [
                106.7588885,
                10.8585592
              ],
              [
                106.7583175,
                10.8580775
              ],
              [
                106.7576906,
                10.8579004
              ],
              [
                106.7573999,
                10.8577403
              ],
              [
                106.7572307,
                10.8575196
              ],
              [
                106.7570006,
                10.8570883
              ],
              [
                106.756921,
                10.8568384
              ],
              [
                106.756408,
                10.8561743
              ],
              [
                106.7557671,
                10.8554586
              ],
              [
                106.755375,
                10.8549104
              ],
              [
                106.7551151,
                10.8545176
              ],
              [
                106.7549251,
                10.8541256
              ],
              [
                106.7547236,
                10.8537317
              ],
              [
                106.7546239,
                10.8534216
              ],
              [
                106.7545993,
                10.8530534
              ],
              [
                106.7547062,
                10.8524338
              ],
              [
                106.7548799,
                10.8515223
              ],
              [
                106.7549411,
                10.8512145
              ],
              [
                106.7549661,
                10.8511412
              ]
            ]
          ]
        ]
      }
    }
  ]
}