{
  "type": "FeatureCollection",
  "hc-transform": {
    "default": {
      "crs": "+proj=longlat +ellps=WGS84 +units=m +no_defs"
    }
  },
  "features": [
    {
      "type": "Feature",
      "properties": {
        "osm-relation-id": 6890771,
        "name": "Phường 10",
        "hc-key": "phuong-10",
        "district": "Quận 8"
      },
      "geometry": {
        "type": "MultiPolygon",
        "coordinates": [
          [
            [
              [
                106.6617055,
                10.7428755
              ],
              [
                106.6615857,
                10.743921
              ],
              [
                106.6616289,
                10.7442116
              ],
              [
                106.6617213,
                10.7446717
              ],
              [
                106.6618445,
                10.7450895
              ],
              [
                106.6621341,
                10.7459249
              ],
              [
                106.6622204,
                10.7461247
              ],
              [
                106.6624422,
                10.7464819
              ],
              [
                106.6626887,
                10.746718
              ],
              [
                106.6629784,
                10.7469057
              ],
              [
                106.6633481,
                10.7470449
              ],
              [
                106.6640802,
                10.7472912
              ],
              [
                106.6644625,
                10.7474181
              ],
              [
                106.66508,
                10.7476163
              ],
              [
                106.6659702,
                10.7479188
              ],
              [
                106.6666957,
                10.7481709
              ],
              [
                106.6674566,
                10.7484074
              ],
              [
                106.6683096,
                10.7486856
              ],
              [
                106.669181,
                10.7489633
              ],
              [
                106.6691433,
                10.748385
              ],
              [
                106.669129,
                10.7482651
              ],
              [
                106.6690799,
                10.7478842
              ],
              [
                106.6689693,
                10.7462615
              ],
              [
                106.6689253,
                10.7462509
              ],
              [
                106.6682445,
                10.7461058
              ],
              [
                106.6673336,
                10.7459239
              ],
              [
                106.6671069,
                10.745895
              ],
              [
                106.6664697,
                10.7457783
              ],
              [
                106.665888,
                10.7456657
              ],
              [
                106.6647248,
                10.7454404
              ],
              [
                106.6647319,
                10.7451515
              ],
              [
                106.6647208,
                10.7448723
              ],
              [
                106.6647352,
                10.7443162
              ],
              [
                106.6647613,
                10.7439633
              ],
              [
                106.6648391,
                10.7434461
              ],
              [
                106.6629061,
                10.7430943
              ],
              [
                106.6617055,
                10.7428755
              ]
            ]
          ]
        ]
      }
    }
  ]
}